Workbook

Sheet Cover
B2: Entrata IPO Valuation Model
B4: Company | C4: Entrata, Inc.
B5: Proposed Ticker | C5: ENT
B6: Prepared By | C6: Nilesh Wagh
B7: Date | C7: June 2026
B8: Purpose | C8: IPO valuation case study model
B10: Model Summary
B11: Target Price | C11: $26/share | E11: IPO Range | F11: $24-$30/share
B12: Primary Method | C12: EV / Forward Revenue | E12: Post-IPO Shares | F12: 205.0M
B13: Key Revenue Driver | C13: Units × ARPU | E13: Base 2026E Revenue | F13: Linked to model
B14: Core Thesis | C14: High-growth profitable vertical SaaS platform with expanding margins and large SAM.
B15: Note | C15: Blue font = hardcoded input; Green font = linked; Black font = formula.

Sheet Assumptions
A1: Assumptions & Model Inputs
A3: Assumption | B3: 2024A | C3: 2025A | D3: 2026E | E3: 2027E | F3: 2028E
A4: Unit Growth | C4: 0.148 | D4: 0.12 | E4: 0.11 | F4: 0.1
A5: ARPU Growth | C5: 0.077 | D5: 0.07 | E5: 0.06 | F5: 0.05
A6: Gross Margin | B6: 0.555 | C6: 0.601 | D6: 0.63 | E6: 0.64 | F6: 0.65
A7: S&M % Revenue | B7: 0.18 | C7: 0.168 | D7: 0.13 | E7: 0.13 | F7: 0.12
A8: R&D % Revenue | B8: 0.146 | C8: 0.144 | D8: 0.13 | E8: 0.12 | F8: 0.12
A9: G&A % Revenue | B9: 0.102 | C9: 0.127 | D9: 0.11 | E9: 0.1 | F9: 0.1
A10: Tax Rate | B10: 0.37 | C10: 0.154 | D10: 0.235 | E10: 0.22 | F10: 0.22
A11: Interest Expense ($M) | B11: 18 | C11: 15.8 | D11: 25.6 | E11: 23 | F11: 20
A12: D&A % Revenue | D12: 0.05 | E12: 0.047 | F12: 0.045
A13: SBC % Revenue | D13: 0.03 | E13: 0.028 | F13: 0.026
A14: Capex % Revenue | D14: 0.02 | E14: 0.02 | F14: 0.02
A15: Net Working Capital % Revenue | D15: 0.02 | E15: 0.02 | F15: 0.02
A16: ARR Growth | C16: 0.21 | D16: 0.19 | E16: 0.17 | F16: 0.15
A17: Net Retention | B17: 1.15 | C17: 1.12 | D17: 1.1 | E17: 1.09 | F17: 1.08
A18: EV/Revenue - Bear | D18: 7
A19: EV/Revenue - Base | D19: 8.5
A20: EV/Revenue - Bull | D20: 10
A21: Post-IPO Shares Outstanding (M) | C21: 205 | D21: 205 | E21: 205 | F21: 205
A22: Net Debt / (Cash) ($M) | C22: 269.698 | D22: 269.698 | E22: 269.698 | F22: 269.698

Sheet KPI Schedule
A1: KPI Schedule
A3: KPI | B3: 2024A | C3: 2025A | D3: 2026E | E3: 2027E | F3: 2028E
A4: Units | B4: 2126338 | C4: 2440976 | D4: =C4*(1+Assumptions!D4) -> 2733893.1 | E4: =D4*(1+Assumptions!E4) -> 3034621.4 | F4: =E4*(1+Assumptions!F4) -> 3338083.5
A5: Unit Growth | C5: =C4/B4-1 -> 0.14797177 | D5: =D4/C4-1 -> 0.12 | E5: =E4/D4-1 -> 0.11 | F5: =F4/E4-1 -> 0.1
A6: ARPU ($) | B6: 194 | C6: 209 | D6: =C6*(1+Assumptions!D5) -> 223.63 | E6: =D6*(1+Assumptions!E5) -> 237.0478 | F6: =E6*(1+Assumptions!F5) -> 248.90019
A7: ARPU Growth | C7: =C6/B6-1 -> 0.077319588 | D7: =D6/C6-1 -> 0.07 | E7: =E6/D6-1 -> 0.06 | F7: =F6/E6-1 -> 0.05
A8: Revenue ($M) | B8: 412 | C8: 509.295 | D8: =D4*D6/1000000 -> 611.38052 | E8: =E4*E6/1000000 -> 719.35032 | F8: =F4*F6/1000000 -> 830.84962
A9: Revenue Growth | C9: =C8/B8-1 -> 0.23615291 | D9: =D8/C8-1 -> 0.20044477 | E9: =E8/D8-1 -> 0.1766 | F9: =F8/E8-1 -> 0.155
A10: ARR ($M) | B10: =C10/(1+Assumptions!C16) -> 442.14876 | C10: 535 | D10: =C10*(1+Assumptions!D16) -> 636.65 | E10: =D10*(1+Assumptions!E16) -> 744.8805 | F10: =E10*(1+Assumptions!F16) -> 856.61257
A11: ARR Growth | B11: 0.13 | C11: =C10/B10-1 -> 0.21 | D11: =D10/C10-1 -> 0.19 | E11: =E10/D10-1 -> 0.17 | F11: =F10/E10-1 -> 0.15
A12: Gross Retention | B12: 0.99 | C12: 0.97 | D12: 0.97 | E12: 0.97 | F12: 0.97
A13: Net Retention | B13: =Assumptions!B17 -> 1.15 | C13: =Assumptions!C17 -> 1.12 | D13: =Assumptions!D17 -> 1.1 | E13: =Assumptions!E17 -> 1.09 | F13: =Assumptions!F17 -> 1.08
A14: Customers > $500K ARR | B14: 183 | C14: 233 | D14: 280 | E14: 326 | F14: 375
A15: % of ARR from >$500K Customers | B15: 0.81 | C15: 0.84 | D15: 0.85 | E15: 0.86 | F15: 0.87
A16: Gross Margin | B16: =Assumptions!B6 -> 0.555 | C16: =Assumptions!C6 -> 0.601 | D16: =Assumptions!D6 -> 0.63 | E16: =Assumptions!E6 -> 0.64 | F16: =Assumptions!F6 -> 0.65
A17: Operating Margin | B17: ='Income Statement'!B15/'Income Statement'!B4 -> 0.12754369 | C17: ='Income Statement'!C15/'Income Statement'!C4 -> 0.16220265 | D17: ='Income Statement'!D15/'Income Statement'!D4 -> 0.26 | E17: ='Income Statement'!E15/'Income Statement'!E4 -> 0.29 | F17: ='Income Statement'!F15/'Income Statement'!F4 -> 0.31
A18: Non-GAAP Operating Margin | B18: 0.14 | C18: 0.23 | D18: 0.25 | E18: 0.27 | F18: 0.29
A19: Free Cash Flow Margin | B19: ='Cash Flow'!B12/'Income Statement'!B4 -> 0.36554369 | C19: ='Cash Flow'!C12/'Income Statement'!C4 -> -0.169177 | D19: ='Cash Flow'!D12/'Income Statement'!D4 -> 0.20717164 | E19: ='Cash Flow'!E12/'Income Statement'!E4 -> 0.22545609 | F19: ='Cash Flow'!F12/'Income Statement'!F4 -> 0.24726831
A20: Commentary | B20: Strong enterprise adoption + high retention | C20: Improved scale + retention | D20: Unit and ARPU expansion | E20: Moderating growth, margin expansion | F20: Mature growth, higher FCF

Sheet Revenue Build
A1: Revenue Build
A3: Revenue Build ($M unless noted) | B3: 2024A | C3: 2025A | D3: 2026E | E3: 2027E | F3: 2028E
A4: Units | B4: ='KPI Schedule'!B4 -> 2126338 | C4: ='KPI Schedule'!C4 -> 2440976 | D4: ='KPI Schedule'!D4 -> 2733893.1 | E4: ='KPI Schedule'!E4 -> 3034621.4 | F4: ='KPI Schedule'!F4 -> 3338083.5
A5: Unit Growth | B5: ='KPI Schedule'!B5 -> 0 | C5: ='KPI Schedule'!C5 -> 0.14797177 | D5: ='KPI Schedule'!D5 -> 0.12 | E5: ='KPI Schedule'!E5 -> 0.11 | F5: ='KPI Schedule'!F5 -> 0.1
A6: ARPU ($) | B6: ='KPI Schedule'!B6 -> 194 | C6: ='KPI Schedule'!C6 -> 209 | D6: ='KPI Schedule'!D6 -> 223.63 | E6: ='KPI Schedule'!E6 -> 237.0478 | F6: ='KPI Schedule'!F6 -> 248.90019
A7: ARPU Growth | B7: ='KPI Schedule'!B7 -> 0 | C7: ='KPI Schedule'!C7 -> 0.077319588 | D7: ='KPI Schedule'!D7 -> 0.07 | E7: ='KPI Schedule'!E7 -> 0.06 | F7: ='KPI Schedule'!F7 -> 0.05
A8: Revenue from Units × ARPU | B8: =B4*B6/1000000 -> 412.50957 | C8: =C4*C6/1000000 -> 510.16398 | D8: =D4*D6/1000000 -> 611.38052 | E8: =E4*E6/1000000 -> 719.35032 | F8: =F4*F6/1000000 -> 830.84962
A9: Reported / Forecast Revenue | B9: ='KPI Schedule'!B8 -> 412 | C9: ='KPI Schedule'!C8 -> 509.295 | D9: ='KPI Schedule'!D8 -> 611.38052 | E9: ='KPI Schedule'!E8 -> 719.35032 | F9: ='KPI Schedule'!F8 -> 830.84962
A10: Revenue Growth | B10: ='KPI Schedule'!B9 -> 0 | C10: ='KPI Schedule'!C9 -> 0.23615291 | D10: ='KPI Schedule'!D9 -> 0.20044477 | E10: ='KPI Schedule'!E9 -> 0.1766 | F10: ='KPI Schedule'!F9 -> 0.155
A11: Revenue by Segment
A12: Subscription-related Revenue | B12: 354.701 | C12: 437.742 | D12: =C12*(1+19.5%) -> 523.10169 | E12: =D12*(1+17.8%) -> 616.21379 | F12: =E12*(1+15%) -> 708.64586
A13: Subscription Revenue Growth | C13: =C12/B12-1 -> 0.23411549 | D13: =D12/C12-1 -> 0.195 | E13: =E12/D12-1 -> 0.178 | F13: =F12/E12-1 -> 0.15
A14: Embedded Technology Solutions Revenue | B14: 57.299 | C14: 71.553 | D14: =C14*(1+24%) -> 88.72572 | E14: =D14*(1+18.5%) -> 105.13998 | F14: =E14*(1+18%) -> 124.06517
A15: Embedded Tech Revenue Growth | C15: =C14/B14-1 -> 0.24876525 | D15: =D14/C14-1 -> 0.24 | E15: =E14/D14-1 -> 0.185 | F15: =F14/E14-1 -> 0.18
A16: Total Segment Revenue | B16: =SUM(B12,B14) -> 412 | C16: =SUM(C12,C14) -> 509.295 | D16: =SUM(D12,D14) -> 611.82741 | E16: =SUM(E12,E14) -> 721.35377 | F16: =SUM(F12,F14) -> 832.71103
A17: Subscription % Total | B17: =B12/B16 -> 0.86092476 | C17: =C12/C16 -> 0.85950579 | D17: =D12/D16 -> 0.85498244 | E17: =E12/E16 -> 0.8542463 | F17: =F12/F16 -> 0.85101053
A18: Embedded Tech % Total | B18: =B14/B16 -> 0.13907524 | C18: =C14/C16 -> 0.14049421 | D18: =D14/D16 -> 0.14501756 | E18: =E14/E16 -> 0.1457537 | F18: =F14/F16 -> 0.14898947

Sheet Income Statement
A1: Income Statement
A3: ($M) | B3: 2024A | C3: 2025A | D3: 2026E | E3: 2027E | F3: 2028E
A4: Revenue | B4: 412 | C4: 509.295 | D4: ='Revenue Build'!D9 -> 611.38052 | E4: ='Revenue Build'!E9 -> 719.35032 | F4: ='Revenue Build'!F9 -> 830.84962
A5: Revenue Growth | C5: =C4/B4-1 -> 0.23615291 | D5: =D4/C4-1 -> 0.20044477 | E5: =E4/D4-1 -> 0.1766 | F5: =F4/E4-1 -> 0.155
A6: Cost of Revenue | B6: 183.272 | C6: 203.143 | D6: =D4*(1-Assumptions!D6) -> 226.21079 | E6: =E4*(1-Assumptions!E6) -> 258.96611 | F6: =F4*(1-Assumptions!F6) -> 290.79737
A7: Gross Profit | B7: 228.728 | C7: 306.152 | D7: =D4-D6 -> 385.16973 | E7: =E4-E6 -> 460.3842 | F7: =F4-F6 -> 540.05225
A8: Gross Margin | B8: =B7/B4 -> 0.55516505 | C8: =C7/C4 -> 0.60112901 | D8: =D7/D4 -> 0.63 | E8: =E7/E4 -> 0.64 | F8: =F7/F4 -> 0.65
A9: Sales & Marketing | B9: 74.043 | C9: 85.725 | D9: =D4*Assumptions!D7 -> 79.479467 | E9: =E4*Assumptions!E7 -> 93.515541 | F9: =F4*Assumptions!F7 -> 99.701954
A10: % Revenue | B10: =B9/B4 -> 0.17971602 | C10: =C9/C4 -> 0.16832091 | D10: =D9/D4 -> 0.13 | E10: =E9/E4 -> 0.13 | F10: =F9/F4 -> 0.12
A11: Research & Product Development | B11: 60.132 | C11: 73.2 | D11: =D4*Assumptions!D8 -> 79.479467 | E11: =E4*Assumptions!E8 -> 86.322038 | F11: =F4*Assumptions!F8 -> 99.701954
A12: % Revenue | B12: =B11/B4 -> 0.14595146 | C12: =C11/C4 -> 0.14372809 | D12: =D11/D4 -> 0.13 | E12: =E11/E4 -> 0.12 | F12: =F11/F4 -> 0.12
A13: General & Administrative | B13: 42.005 | C13: 64.618 | D13: =D4*Assumptions!D9 -> 67.251857 | E13: =E4*Assumptions!E9 -> 71.935032 | F13: =F4*Assumptions!F9 -> 83.084962
A14: % Revenue | B14: =B13/B4 -> 0.10195388 | C14: =C13/C4 -> 0.12687735 | D14: =D13/D4 -> 0.11 | E14: =E13/E4 -> 0.1 | F14: =F13/F4 -> 0.1
A15: Operating Income | B15: 52.548 | C15: 82.609 | D15: =D7-D9-D11-D13 -> 158.95893 | E15: =E7-E9-E11-E13 -> 208.61159 | F15: =F7-F9-F11-F13 -> 257.56338
A16: Operating Margin | B16: =B15/B4 -> 0.12754369 | C16: =C15/C4 -> 0.16220265 | D16: =D15/D4 -> 0.26 | E16: =E15/E4 -> 0.29 | F16: =F15/F4 -> 0.31
A17: Interest Expense | B17: 17.984 | C17: 15.79 | D17: =Assumptions!D11 -> 25.6 | E17: =Assumptions!E11 -> 23 | F17: =Assumptions!F11 -> 20
A18: Other Expense / Income | B18: 0.031 | C18: 2.715 | D18: 0 | E18: 0 | F18: 0
A19: Loss on Debt Extinguishment | B19: 0 | C19: 4.188 | D19: 0 | E19: 0 | F19: 0
A20: Income Before Tax | B20: 34.533 | C20: 59.916 | D20: =D15-D17-D18-D19 -> 133.35893 | E20: =E15-E17-E18-E19 -> 185.61159 | F20: =F15-F17-F18-F19 -> 237.56338
A21: Tax Expense | B21: 12.774 | C21: 9.24 | D21: =D20*Assumptions!D10 -> 31.33935 | E21: =E20*Assumptions!E10 -> 40.83455 | F21: =F20*Assumptions!F10 -> 52.263944
A22: Tax Rate | B22: =B21/B20 -> 0.36990705 | C22: =C21/C20 -> 0.1542159 | D22: =D21/D20 -> 0.235 | E22: =E21/E20 -> 0.22 | F22: =F21/F20 -> 0.22
A23: Net Income | B23: 21.759 | C23: 50.676 | D23: =D20-D21 -> 102.01959 | E23: =E20-E21 -> 144.77704 | F23: =F20-F21 -> 185.29944
A24: Net Margin | B24: =B23/B4 -> 0.052813107 | C24: =C23/C4 -> 0.099502253 | D24: =D23/D4 -> 0.16686758 | E24: =E23/E4 -> 0.20126083 | F24: =F23/F4 -> 0.22302404

Sheet Balance Sheet
A1: Balance Sheet
A3: ($M) | B3: 2024A | C3: 2025A | D3: 2026E | E3: 2027E | F3: 2028E
A4: Cash & Equivalents | B4: 43.312 | C4: 95.111 | D4: 119.94 | E4: =D4+'Cash Flow'!E10-'Cash Flow'!E11 -> 282.12191 | F4: =E4+'Cash Flow'!F10-'Cash Flow'!F11 -> 487.5647
A5: Designated Cash | B5: 267.36 | C5: 272.017 | D5: 299.062 | E5: =D5 -> 299.062 | F5: =E5 -> 299.062
A6: Restricted Cash | B6: 8.587 | C6: 11.643 | D6: 12.333 | E6: =D6 -> 12.333 | F6: =E6 -> 12.333
A7: Accounts Receivable | B7: 29.874 | C7: 38.437 | D7: ='Income Statement'!D4*7.5% -> 45.853539 | E7: ='Income Statement'!E4*7.5% -> 53.951274 | F7: ='Income Statement'!F4*7.5% -> 62.313721
A8: Deferred Contract Costs | B8: 47.969 | C8: 49.077 | D8: ='Income Statement'!D4*9.6% -> 58.69253 | E8: ='Income Statement'!E4*9.6% -> 69.057631 | F8: ='Income Statement'!F4*9.6% -> 79.761563
A9: Prepaids & Other Current Assets | B9: 13.414 | C9: 22.899 | D9: =514.554-SUM(D4:D8) -> -21.327069 | E9: ='Income Statement'!E4*3.5% -> 25.177261 | F9: ='Income Statement'!F4*3.5% -> 29.079737
A10: Total Current Assets | B10: 389.179 | C10: 467.455 | D10: 514.554 | E10: =SUM(E4:E9) -> 741.70308 | F10: =SUM(F4:F9) -> 970.11472
A11: PP&E, Net | B11: 18.17 | C11: 20.394 | D11: ='Income Statement'!D4*3.3% -> 20.175557 | E11: ='Income Statement'!E4*3.3% -> 23.73856 | F11: ='Income Statement'!F4*3.3% -> 27.418037
A12: ROU Assets | B12: 9.804 | C12: 22.266 | D12: 28.5 | E12: =D12*1.02 -> 29.07 | F12: =E12*1.02 -> 29.6514
A13: Intangible Assets, Net | B13: 49.889 | C13: 39.828 | D13: 37.287 | E13: =D13-8.9 -> 28.387 | F13: =E13-6.6 -> 21.787
A14: Goodwill | B14: 185.575 | C14: 192.409 | D14: 192.671 | E14: =D14 -> 192.671 | F14: =E14 -> 192.671
A15: Other Assets | B15: 26.733 | C15: 24.651 | D15: =839.509-SUM(D10:D14) -> 46.321443 | E15: ='Income Statement'!E4*3.5% -> 25.177261 | F15: ='Income Statement'!F4*3.5% -> 29.079737
A16: Total Assets | B16: 700.687 | C16: 788.732 | D16: 839.509 | E16: =SUM(E10:E15) -> 1040.7469 | F16: =SUM(F10:F15) -> 1270.7219
A17: Accounts Payable | B17: 8.571 | C17: 7.923 | D17: ='Income Statement'!D4*1.6% -> 9.7820883 | E17: ='Income Statement'!E4*1.6% -> 11.509605 | F17: ='Income Statement'!F4*1.6% -> 13.293594
A18: Accrued Expenses & Other Current Liabilities | B18: 40.184 | C18: 51.025 | D18: ='Income Statement'!D4*7% -> 42.796636 | E18: ='Income Statement'!E4*7% -> 50.354522 | F18: ='Income Statement'!F4*7% -> 58.159473
A19: Deferred Revenue | B19: 7.482 | C19: 10.134 | D19: ='Income Statement'!D4*2% -> 12.22761 | E19: ='Income Statement'!E4*2% -> 14.387006 | F19: ='Income Statement'!F4*2% -> 16.616992
A20: Customer Deposits | B20: 266.312 | C20: 270.904 | D20: =270.9 -> 270.9 | E20: =D20 -> 270.9 | F20: =E20 -> 270.9
A21: Debt | B21: 168.404 | C21: 390.25 | D21: 389.638 | E21: =D21-'Cash Flow'!E11 -> 369.638 | F21: =E21-'Cash Flow'!F11 -> 349.638
A22: Lease Liabilities | B22: 13.934 | C22: 25.259 | D22: 31.433 | E22: =D22*0.98 -> 30.80434 | F22: =E22*0.98 -> 30.188253
A23: Other Liabilities | B23: 5.525 | C23: 5.467 | D23: =782.94-SUM(D17:D22) -> 26.162665 | E23: =D23 -> 26.162665 | F23: =E23 -> 26.162665
A24: Total Liabilities | B24: 505.512 | C24: 756.326 | D24: 782.94 | E24: =SUM(E17:E23) -> 773.75614 | F24: =SUM(F17:F23) -> 764.95898
A25: Stockholders' Equity | B25: 195.175 | C25: 32.406 | D25: 56.569 | E25: =E16-E24 -> 266.99076 | F25: =F16-F24 -> 505.76291
A26: Total Liabilities + Equity | B26: =B24+B25 -> 700.687 | C26: =C24+C25 -> 788.732 | D26: =D24+D25 -> 839.509 | E26: =E24+E25 -> 1040.7469 | F26: =F24+F25 -> 1270.7219
A27: Balance Check | B27: =B16-B26 -> 0 | C27: =C16-C26 -> 0 | D27: =D16-D26 -> 0 | E27: =E16-E26 -> 0 | F27: =F16-F26 -> 0

Sheet Cash Flow
A1: Cash Flow Statement
A3: ($M) | B3: 2024A | C3: 2025A | D3: 2026E | E3: 2027E | F3: 2028E
A4: Net Income | B4: 21.759 | C4: 50.676 | D4: ='Income Statement'!D23 -> 102.01959 | E4: ='Income Statement'!E23 -> 144.77704 | F4: ='Income Statement'!F23 -> 185.29944
A5: D&A | B5: 20.045 | C5: 21.378 | D5: ='Income Statement'!D4*Assumptions!D12 -> 30.569026 | E5: ='Income Statement'!E4*Assumptions!E12 -> 33.809465 | F5: ='Income Statement'!F4*Assumptions!F12 -> 37.388233
A6: Stock-Based Compensation | B6: 1.791 | C6: 22.014 | D6: ='Income Statement'!D4*Assumptions!D13 -> 18.341416 | E6: ='Income Statement'!E4*Assumptions!E13 -> 20.141809 | F6: ='Income Statement'!F4*Assumptions!F13 -> 21.60209
A7: Change in Net Working Capital / Other | B7: 118.333 | C7: 5.995 | D7: =-(('Income Statement'!D4-'Income Statement'!C4)*Assumptions!D15) -> -2.0417104 | E7: =-(('Income Statement'!E4-'Income Statement'!D4)*Assumptions!E15) -> -2.159396 | F7: =-(('Income Statement'!F4-'Income Statement'!E4)*Assumptions!F15) -> -2.229986
A8: Operating Cash Flow | B8: 161.928 | C8: 100.063 | D8: =D4+D5+D6+D7 -> 148.88832 | E8: =E4+E5+E6+E7 -> 196.56892 | F8: =F4+F5+F6+F7 -> 242.05977
A9: Capex / Purchases of PPE & Software | B9: 9.574 | C9: 12.974 | D9: ='Income Statement'!D4*Assumptions!D14 -> 12.22761 | E9: ='Income Statement'!E4*Assumptions!E14 -> 14.387006 | F9: ='Income Statement'!F4*Assumptions!F14 -> 16.616992
A10: Free Cash Flow | B10: 152.354 | C10: 87.089 | D10: =D8-D9 -> 136.66071 | E10: =E8-E9 -> 182.18191 | F10: =F8-F9 -> 225.44278
A11: Debt Repayment | B11: 1.75 | C11: 173.25 | D11: 10 | E11: 20 | F11: 20
A12: Cash Flow After Debt Repayment | B12: =B10-B11 -> 150.604 | C12: =C10-C11 -> -86.161 | D12: =D10-D11 -> 126.66071 | E12: =E10-E11 -> 162.18191 | F12: =F10-F11 -> 205.44278
A13: Ending Cash | B13: ='Balance Sheet'!B4 -> 43.312 | C13: ='Balance Sheet'!C4 -> 95.111 | D13: ='Balance Sheet'!D4 -> 119.94 | E13: ='Balance Sheet'!E4 -> 282.12191 | F13: ='Balance Sheet'!F4 -> 487.5647
A15: FCF Margin | B15: =B10/'Income Statement'!B4 -> 0.36979126 | C15: =C10/'Income Statement'!C4 -> 0.17099913 | D15: =D10/'Income Statement'!D4 -> 0.22352807 | E15: =E10/'Income Statement'!E4 -> 0.25325896 | F15: =F10/'Income Statement'!F4 -> 0.27134006
A16: Source / note | B16: Historical from S-1 | C16: Historical from S-1 | D16: Forecast: CFO less capex | E16: Forecast: CFO less capex | F16: Forecast: CFO less capex

Sheet Valuation
A1: Relative Valuation & IPO Price Range
A3: Peer | B3: Category | C3: EV/Revenue | D3: EV/EBITDA | E3: Notes
A4: AppFolio | B4: Property management SaaS | C4: 8.5 | D4: 26 | E4: Closest public comp; update with live market data
A5: Procore | B5: Vertical SaaS | C5: 8.8 | D5: 30 | E5: Construction software vertical SaaS
A6: Guidewire | B6: Insurance vertical SaaS | C6: 10.2 | D6: 28 | E6: Enterprise vertical software
A7: Workiva | B7: Cloud compliance software | C7: 9.5 | D7: 27 | E7: Recurring revenue SaaS
A8: BlackLine | B8: Financial SaaS | C8: 7.5 | D8: 22 | E8: Mature SaaS comp
A9: Median | C9: =MEDIAN(C4:C8) -> 8.8 | D9: =MEDIAN(D4:D8) -> 27 | E9: Peer median used to frame base case
A12: Scenario | B12: EV/Revenue Multiple | C12: 2026E Revenue | D12: Enterprise Value | E12: Net Debt / (Cash) | F12: Equity Value
A13: Bear | B13: =Assumptions!D18 -> 7 | C13: ='Income Statement'!D4 -> 611.38052 | D13: =B13*C13 -> 4279.6636 | E13: =Assumptions!C22 -> 269.698 | F13: =D13-E13 -> 4009.9656
A14: Base | B14: =Assumptions!D19 -> 8.5 | C14: ='Income Statement'!D4 -> 611.38052 | D14: =B14*C14 -> 5196.7344 | E14: =Assumptions!C22 -> 269.698 | F14: =D14-E14 -> 4927.0364
A15: Bull | B15: =Assumptions!D20 -> 10 | C15: ='Income Statement'!D4 -> 611.38052 | D15: =B15*C15 -> 6113.8052 | E15: =Assumptions!C22 -> 269.698 | F15: =D15-E15 -> 5844.1072
A17: Post-IPO Shares Outstanding (M) | B17: =Assumptions!C21 -> 205 | C17: Provided in case study PDF
A18: Target Price / Share - Base | B18: =F14/B17 -> 24.034324 | C18: Equity Value / Shares
A20: Price per Share Sensitivity | B20: 7 | C20: 8 | D20: 8.5 | E20: 9 | F20: 10
A21: Revenue -10% | B21: =((B$20*'Income Statement'!$D$4*0.9)-Assumptions!$C$22)/Assumptions!$C$21 -> 17.473167 | C21: =((C$20*'Income Statement'!$D$4*0.9)-Assumptions!$C$22)/Assumptions!$C$21 -> 20.157277 | D21: =((D$20*'Income Statement'!$D$4*0.9)-Assumptions!$C$22)/Assumptions!$C$21 -> 21.499332 | E21: =((E$20*'Income Statement'!$D$4*0.9)-Assumptions!$C$22)/Assumptions!$C$21 -> 22.841386 | F21: =((F$20*'Income Statement'!$D$4*0.9)-Assumptions!$C$22)/Assumptions!$C$21 -> 25.525496
A22: Base Revenue | B22: =((B$20*'Income Statement'!$D$4*1)-Assumptions!$C$22)/Assumptions!$C$21 -> 19.560808 | C22: =((C$20*'Income Statement'!$D$4*1)-Assumptions!$C$22)/Assumptions!$C$21 -> 22.543152 | D22: =((D$20*'Income Statement'!$D$4*1)-Assumptions!$C$22)/Assumptions!$C$21 -> 24.034324 | E22: =((E$20*'Income Statement'!$D$4*1)-Assumptions!$C$22)/Assumptions!$C$21 -> 25.525496 | F22: =((F$20*'Income Statement'!$D$4*1)-Assumptions!$C$22)/Assumptions!$C$21 -> 28.50784
A23: Revenue +10% | B23: =((B$20*'Income Statement'!$D$4*1.1)-Assumptions!$C$22)/Assumptions!$C$21 -> 21.648449 | C23: =((C$20*'Income Statement'!$D$4*1.1)-Assumptions!$C$22)/Assumptions!$C$21 -> 24.929027 | D23: =((D$20*'Income Statement'!$D$4*1.1)-Assumptions!$C$22)/Assumptions!$C$21 -> 26.569316 | E23: =((E$20*'Income Statement'!$D$4*1.1)-Assumptions!$C$22)/Assumptions!$C$21 -> 28.209606 | F23: =((F$20*'Income Statement'!$D$4*1.1)-Assumptions!$C$22)/Assumptions!$C$21 -> 31.490184
A26: Recommended IPO Valuation Range
A27: Low Price / Share | B27: =ROUND(B18*0.92,0) -> 22 | C27: Base case minus discount for IPO execution risk
A28: Target Price / Share | B28: =ROUND(B18,0) -> 24 | C28: Base case target
A29: High Price / Share | B29: =ROUND(B18*1.08,0) -> 26 | C29: Bullish scenario with stronger ARPU/AI uptake
A30: Implied EV/Revenue at Target | B30: =((B28*Assumptions!C21)+Assumptions!C22)/'Income Statement'!D4 -> 8.488491 | C30: Target price × shares + net debt / 2026E revenue
A31: Investment View | B31: Subscribe / Positive | C31: Attractive vertical SaaS IPO with strong unit/ARPU growth and margin expansion

Sheet Interactive Dashboard
A1: ENTRATA IPO VALUATION DASHBOARD
A3: Case Study: IPO Valuation | Units: $mm except per-share, multiples, units and ARPU
A5: Scenario Selector | B5: Target | D5: Selected Price | E5: =IF(B5="Low",22,IF(B5="Target",24,IF(B5="High",26,""))) -> 24 | G5: Use the dropdown in B5 to switch Low / Target / High pricing.
A7: 2025 Revenue $509.3M | C7: 2025 Revenue Growth 23.6% | E7: 2025 Gross Margin 60.1% | G7: 2025 Operating Margin 16.2% | I7: Target Price $24 | K7: IPO Range $22 - $26
I9: =E5 -> 24
A11: 2026E Revenue $611.4M | C11: 2026E Revenue Growth 20.0% | E11: 2025 Units 2.44M | G11: 2025 ARPU $209.0 | I11: Base EV/Revenue 8.5x | K11: Recommendation SUBSCRIBE
A15: Historical & Forecast Operating Metrics | H15: Valuation Summary & Interactive Scenario
A16: Year | B16: Revenue | C16: Gross Margin | D16: Operating Margin | E16: Units | F16: ARPU | H16: Scenario | I16: Implied EV/Revenue | J16: Price / Share | K16: Metric | L16: Value | M16: Comment
A17: 2024A | B17: 412 | C17: 0.555 | D17: 0.128 | E17: 2126338 | F17: 194 | H17: Low | I17: 7.8 | J17: 22 | K17: Post-IPO shares (M) | L17: 205 | M17: Case study input
A18: 2025A | B18: 509.3 | C18: 0.601 | D18: 0.162 | E18: 2440976 | F18: 209 | H18: Target | I18: 8.5 | J18: 24 | K18: 2026E Revenue | L18: 611.4 | M18: KPI-driven forecast
A19: 2026E | B19: 611.4 | C19: 0.63 | D19: 0.26 | E19: 2733893 | F19: 223.6 | H19: High | I19: 9.2 | J19: 26 | K19: Peer median EV/Revenue | L19: 8.8 | M19: Relative valuation
A20: 2027E | B20: 719.4 | C20: 0.64 | D20: 0.29 | E20: 3034621 | F20: 237 | H20: Selected | I20: =IF(B5="Low",I17,IF(B5="Target",I18,IF(B5="High",I19,""))) -> 8.5 | J20: =E5 -> 24 | K20: Recommendation | L20: SUBSCRIBE | M20: Positive / Subscribe
A21: 2028E | B21: 830.8 | C21: 0.65 | D21: 0.31 | E21: 3338083 | F21: 248.9
A23: Investment Thesis
A24: Recommendation SUBSCRIBE Target Price: $24 IPO Range: $22 - $26 | E24: Key Drivers • 20%+ 2026E revenue growth • 97% gross retention • Enterprise customer concentration • Operating leverage from vertical SaaS | J24: Key Risks • Competition • Payments exposure • Customer expansion risk • Controlled-company governance

Sheet Chart_Data
A1: Year | B1: Revenue ($M) | C1: Units (M) | D1: ARPU ($) | E1: Gross Margin | F1: Operating Margin
A2: 2024A | B2: 412 | C2: 2.126338 | D2: 194 | E2: 0.555 | F2: 0.128
A3: 2025A | B3: 509.3 | C3: 2.440976 | D3: 209 | E3: 0.601 | F3: 0.162
A4: 2026E | B4: 611.4 | C4: 2.733893 | D4: 223.6 | E4: 0.63 | F4: 0.26
A5: 2027E | B5: 719.4 | C5: 3.034621 | D5: 237 | E5: 0.64 | F5: 0.29
A6: 2028E | B6: 830.8 | C6: 3.338083 | D6: 248.9 | E6: 0.65 | F6: 0.31
A8: Scenario | B8: Implied EV/Revenue | C8: Price / Share | E8: Units & ARPU Growth Index Table
A9: Low | B9: 7.8 | C9: 22
A10: Target | B10: 8.5 | C10: 24 | E10: Year | F10: Units Index | G10: ARPU Index
A11: High | B11: 9.2 | C11: 26 | E11: 2024A | F11: 100 | G11: 100
E12: 2025A | F12: ='KPI Schedule'!C4/'KPI Schedule'!B4*100 -> 114.79718 | G12: ='KPI Schedule'!C6/'KPI Schedule'!B6*100 -> 107.73196
A13: Investment Thesis Driver | B13: Weight | E13: 2026E | F13: ='KPI Schedule'!D4/'KPI Schedule'!B4*100 -> 128.57284 | G13: ='KPI Schedule'!D6/'KPI Schedule'!B6*100 -> 115.2732
A14: Revenue Growth | B14: 0.35 | E14: 2027E | F14: ='KPI Schedule'!E4/'KPI Schedule'!B4*100 -> 142.71585 | G14: ='KPI Schedule'!E6/'KPI Schedule'!B6*100 -> 122.18959
A15: Margin Expansion | B15: 0.25 | E15: 2028E | F15: ='KPI Schedule'!F4/'KPI Schedule'!B4*100 -> 156.98744 | G15: ='KPI Schedule'!F6/'KPI Schedule'!B6*100 -> 128.29907
A16: Retention | B16: 0.2
A17: AI Opportunity | B17: 0.2
